pypkg/__init__.py
pypkg/exceptions.py
pypkg/cli/about.py
pypkg/cli/add.py
pypkg/cli/chenge_version.py
pypkg/cli/exceptions.py
pypkg/cli/info.py
pypkg/cli/init.py
pypkg/cli/install.py
pypkg/cli/main.py
pypkg/cli/commands/command.py
pypkg/core/sysinfo.py
sakurapkg-0.1.0.dist-info/LICENSE
sakurapkg-0.1.0.dist-info/METADATA
sakurapkg-0.1.0.dist-info/WHEEL
sakurapkg-0.1.0.dist-info/entry_points.txt
sakurapkg-0.1.0.dist-info/top_level.txt
sakurapkg-0.1.0.dist-info/RECORD
